strataer/__init__.py
strataer/cli/__init__.py
strataer/cli/runner.py
strataer/cmip7/__init__.py
strataer/cmip7/convert_cmip7.py
strataer/eva/__init__.py
strataer/eva/convert_eva.py
strataer/utils/__init__.py
strataer/utils/bounds.py
strataer/utils/canesm.py
strataer/utils/compare.py
strataer/utils/physics.py
strataer/utils/regridding.py
strataer-0.1.3.dist-info/METADATA
strataer-0.1.3.dist-info/WHEEL
strataer-0.1.3.dist-info/entry_points.txt
strataer-0.1.3.dist-info/top_level.txt
strataer-0.1.3.dist-info/RECORD
