Metadata-Version: 2.2
Name: strataer
Version: 0.1.3
Summary: CanESM tools for processing stratospheric aerosol
Author-email: Landon Rieger <landon.rieger@ec.gc.ca>
License: MIT License
Requires-Python: >=3.10
Requires-Dist: numpy
Requires-Dist: xarray>=2024.01.0
Requires-Dist: click
Requires-Dist: dask
Requires-Dist: scipy
Provides-Extra: test
Requires-Dist: pytest; extra == "test"
Requires-Dist: pytest-cov; extra == "test"
Provides-Extra: lint
Requires-Dist: black; extra == "lint"
